kquery/__init__.py
kquery/cli.py
kquery/kquery.py
kquery/forms/__init__.py
kquery/forms/connection.py
kquery/forms/connections.py
kquery/forms/mainwindow.py
kquery-0.0.3.dist-info/METADATA
kquery-0.0.3.dist-info/RECORD
kquery-0.0.3.dist-info/WHEEL
kquery-0.0.3.dist-info/entry_points.txt
kquery-0.0.3.dist-info/top_level.txt
