Metadata-Version: 2.1
Name: kquery
Version: 0.0.3
Summary: Damn small QT based database client
Home-page: https://github.com/samambaman/kquery
Author: Felipe Ferreira
Author-email: felipe.gomes.ferreira@gmail.com
License: UNKNOWN
Keywords: postgresql database client qt pyqt
Platform: UNKNOWN
Classifier: Programming Language :: Python :: 3.5
Classifier: Programming Language :: Python :: 3.6
Classifier: License :: OSI Approved :: MIT License
Classifier: Operating System :: OS Independent
Classifier: Topic :: Database
Classifier: Topic :: Software Development :: Libraries :: Python Modules
Classifier: Topic :: Utilities
Requires-Dist: psycopg2-binary
Requires-Dist: PyQt5
